parasite/__init__.py
parasite/_const.py
parasite/_utils.py
parasite/any.py
parasite/array.py
parasite/boolean.py
parasite/errors.py
parasite/never.py
parasite/null.py
parasite/number.py
parasite/object.py
parasite/string.py
parasite/type.py
parasite/variant.py
parasite-0.1.10.dist-info/LICENSE
parasite-0.1.10.dist-info/METADATA
parasite-0.1.10.dist-info/WHEEL
parasite-0.1.10.dist-info/RECORD
