Metadata-Version: 2.1
Name: parasite
Version: 0.1.10
Summary: Data validation for Python 3
Home-page: https://hendrikboeck.github.io/parasite
License: MIT
Keywords: data,validation,python,zod,datastructures,types,objects,schema,runtime-evaluation
Author: Hendrik Boeck
Author-email: hendrikboeck.dev@protonmail.com
Requires-Python: >=3.11,<4.0
Classifier: Development Status :: 2 - Pre-Alpha
Classifier: Environment :: Console
Classifier: Intended Audience :: Developers
Classifier: License :: OSI Approved :: MIT License
Classifier: Operating System :: MacOS
Classifier: Operating System :: Microsoft :: Windows
Classifier: Operating System :: OS Independent
Classifier: Operating System :: POSIX
Classifier: Programming Language :: Python :: 3
Classifier: Programming Language :: Python :: 3.11
Classifier: Programming Language :: Python :: 3.12
Classifier: Topic :: Software Development :: Libraries
Classifier: Topic :: Software Development :: Libraries :: Python Modules
Classifier: Typing :: Typed
Requires-Dist: rusttypes (>=0.1.0,<0.2.0)
Requires-Dist: tracing-py3 (>=0.1.0,<0.2.0)
Project-URL: Documentation, https://hendrikboeck.github.io/parasite
Project-URL: Repository, https://github.com/hendrikboeck/parasite
